helloworldpkg/__init__.py
helloworldpkg/hello_world.py
helloworldpkg-0.0.2.dist-info/METADATA
helloworldpkg-0.0.2.dist-info/WHEEL
helloworldpkg-0.0.2.dist-info/top_level.txt
helloworldpkg-0.0.2.dist-info/RECORD
