Metadata-Version: 2.1
Name: helloworldpkg
Version: 0.0.2
Summary: Just hello world
Home-page: UNKNOWN
Author: Gokuruto
Author-email: <mail@neuralnine.com>
License: UNKNOWN
Keywords: python
Platform: UNKNOWN
Classifier: Programming Language :: Python :: 3
Classifier: Operating System :: Unix
Classifier: Operating System :: MacOS :: MacOS X
Classifier: Operating System :: Microsoft :: Windows
